metapensiero.extjs.desktop-2.4-py3.10-nspkg.pth
metapensiero/extjs/desktop/__init__.py
metapensiero/extjs/desktop/__main__.py
metapensiero/extjs/desktop/pyramid.py
metapensiero/extjs/desktop/assets/css/action.css
metapensiero/extjs/desktop/assets/css/desktop.css
metapensiero/extjs/desktop/assets/css/filterbar.css
metapensiero/extjs/desktop/assets/css/form.css
metapensiero/extjs/desktop/assets/css/grid.css
metapensiero/extjs/desktop/assets/css/upload.css
metapensiero/extjs/desktop/assets/images/action/add.png
metapensiero/extjs/desktop/assets/images/action/arrow_undo.png
metapensiero/extjs/desktop/assets/images/action/delete.png
metapensiero/extjs/desktop/assets/images/action/disk.png
metapensiero/extjs/desktop/assets/images/action/edit.png
metapensiero/extjs/desktop/assets/images/desktop/caution.gif
metapensiero/extjs/desktop/assets/images/desktop/clock.gif
metapensiero/extjs/desktop/assets/images/desktop/hourglass.gif
metapensiero/extjs/desktop/assets/images/desktop/logout.png
metapensiero/extjs/desktop/assets/images/desktop/menu.png
metapensiero/extjs/desktop/assets/images/desktop/quote.gif
metapensiero/extjs/desktop/assets/images/desktop/sencha.gif
metapensiero/extjs/desktop/assets/images/desktop/user.png
metapensiero/extjs/desktop/assets/images/desktop/user_gray.png
metapensiero/extjs/desktop/assets/images/desktop/user_suit.png
metapensiero/extjs/desktop/assets/images/filterbar/clear-filters.png
metapensiero/extjs/desktop/assets/images/filterbar/clear-text.gif
metapensiero/extjs/desktop/assets/images/filterbar/filter.png
metapensiero/extjs/desktop/assets/images/filterbar/operator-eq.gif
metapensiero/extjs/desktop/assets/images/filterbar/operator-gt.gif
metapensiero/extjs/desktop/assets/images/filterbar/operator-gte.gif
metapensiero/extjs/desktop/assets/images/filterbar/operator-like.gif
metapensiero/extjs/desktop/assets/images/filterbar/operator-lt.gif
metapensiero/extjs/desktop/assets/images/filterbar/operator-lte.gif
metapensiero.extjs.desktop-2.4.dist-info/METADATA
metapensiero.extjs.desktop-2.4.dist-info/WHEEL
metapensiero.extjs.desktop-2.4.dist-info/entry_points.txt
metapensiero.extjs.desktop-2.4.dist-info/namespace_packages.txt
metapensiero.extjs.desktop-2.4.dist-info/pbr.json
metapensiero.extjs.desktop-2.4.dist-info/top_level.txt
metapensiero.extjs.desktop-2.4.dist-info/RECORD
