Metadata-Version: 2.1
Name: metapensiero.extjs.desktop
Version: 2.4
Summary: An ExtJS 4 desktop application packaged with extra goodies
Home-page: https://gitlab.com/metapensiero/metapensiero.extjs.desktop
Author: Lele Gaifax
Author-email: lele@metapensiero.it
License: GPLv3+
Classifier: Programming Language :: Python
Classifier: Programming Language :: Python :: 3 :: Only
Classifier: Programming Language :: Python :: 3.9
Classifier: License :: OSI Approved :: GNU General Public License v3 or later (GPLv3+)
Classifier: Topic :: Internet :: WWW/HTTP :: WSGI :: Application
Provides-Extra: dev
